asyncpg_recorder/__init__.py
asyncpg_recorder/config.py
asyncpg_recorder/main.py
asyncpg_recorder/plugin.py
asyncpg_recorder-0.4.0.dist-info/licenses/COPYING
asyncpg_recorder-0.4.0.dist-info/licenses/COPYING.LESSER
asyncpg_recorder-0.4.0.dist-info/WHEEL
asyncpg_recorder-0.4.0.dist-info/entry_points.txt
asyncpg_recorder-0.4.0.dist-info/METADATA
asyncpg_recorder-0.4.0.dist-info/RECORD
