Metadata-Version: 2.4
Name: asyncpg-recorder
Version: 0.4.0
Summary: Automatically mock your Postgres interactions to simplify and speed up testing
Author: HeiGIT ohsome team
Author-email: HeiGIT ohsome team <ohsome@heigit.org>
License-Expression: LGPL-3.0-only
License-File: COPYING
License-File: COPYING.LESSER
Classifier: Framework :: Pytest
Classifier: Intended Audience :: Developers
Classifier: License :: OSI Approved :: GNU Lesser General Public License v3 (LGPLv3)
Classifier: Programming Language :: Python :: 3 :: Only
Classifier: Programming Language :: Python :: 3.11
Classifier: Programming Language :: Python :: 3.12
Classifier: Programming Language :: Python :: 3.13
Classifier: Topic :: Software Development :: Libraries :: Python Modules
Classifier: Topic :: Software Development :: Testing
Requires-Dist: asyncpg>=0.30.0
Requires-Dist: testcontainers[postgres]>=4.9.1
Requires-Python: >=3.11, <3.14
Project-URL: Changelog, https://github.com/GIScience/asyncpg-recorder/blob/main/CHANGELOG.md
Project-URL: Documentation, https://github.com/GIScience/asyncpg-recorder/blob/main/README.md
Project-URL: Homepage, https://ohsome.org/
Project-URL: Issues, https://github.com/GIScience/asyncpg-recorder/issues
Project-URL: Repository, https://github.com/GIScience/asyncpg-recorder
